mkdocs_nav_async/__init__.py
mkdocs_nav_async/plugin.py
mkdocs_nav_async/loading_icons/bars.svg
mkdocs_nav_async-0.26.dist-info/LICENSE
mkdocs_nav_async-0.26.dist-info/METADATA
mkdocs_nav_async-0.26.dist-info/WHEEL
mkdocs_nav_async-0.26.dist-info/entry_points.txt
mkdocs_nav_async-0.26.dist-info/top_level.txt
mkdocs_nav_async-0.26.dist-info/RECORD
