Metadata-Version: 2.2
Name: mkdocs-nav-async
Version: 0.26
Summary: MkDocs plugin to extract navigation and load it asynchronously
Home-page: https://github.com/0x10-z/mkdocs-nav-async
Author: Iker Ocio (0x10)
License-File: LICENSE
Requires-Dist: mkdocs
Requires-Dist: lxml
Requires-Dist: htmlmin
Dynamic: author
Dynamic: description
Dynamic: description-content-type
Dynamic: home-page
Dynamic: requires-dist
Dynamic: summary
